fawern/__init__.py
fawern/base_assistant.py
fawern/chat_python.py
fawern/code_file_name_generator.py
fawern/get_code_from_input.py
fawern/save_to_md.py
tests/__init__.py
tests/test_chat_python.py
fawern-0.2.5.dist-info/LICENSE
fawern-0.2.5.dist-info/METADATA
fawern-0.2.5.dist-info/WHEEL
fawern-0.2.5.dist-info/top_level.txt
fawern-0.2.5.dist-info/RECORD
