Metadata-Version: 2.1
Name: fawern
Version: 0.2.5
Summary: Fawern AI, A Python Developer AI Assistant
Home-page: https://github.com/fawern/fawern_ai
Author: Enes Ekinci
Author-email: ekincimuhammedenes13@gmai.com
License: MIT
Classifier: Programming Language :: Python :: 3
Classifier: License :: OSI Approved :: MIT License
Classifier: Operating System :: OS Independent
Requires-Python: >=3.6
License-File: LICENSE
Requires-Dist: groq ==0.9.0
Requires-Dist: python-dotenv ==1.0.1
Requires-Dist: setuptools ==69.0.3
